edgar_connect/__init__.py
edgar_connect/_version.py
edgar_connect/edgar_connect.py
edgar_connect/exceptions.py
edgar_connect/user_agent.py
edgar_connect-0.1.2.dist-info/LICENSE
edgar_connect-0.1.2.dist-info/METADATA
edgar_connect-0.1.2.dist-info/WHEEL
edgar_connect-0.1.2.dist-info/top_level.txt
edgar_connect-0.1.2.dist-info/RECORD
