Metadata-Version: 2.1
Name: edgar-connect
Version: 0.1.2
Summary: Download EDGAR filings
Author-email: Jesse Grabowski <jessegrabowski@gmail.com>
License: GNU GENERAL PUBLIC LICENSE
Keywords: finance,economics,financial economics,securities,stocks,stock market,corporate finance
Classifier: Development Status :: 2 - Pre-Alpha
Classifier: Intended Audience :: Science/Research
Classifier: Programming Language :: Python
Classifier: Operating System :: Microsoft :: Windows
Classifier: Operating System :: POSIX
Classifier: Operating System :: Unix
Classifier: Operating System :: MacOS
Classifier: Programming Language :: Python :: 3.11
Classifier: Programming Language :: Python :: 3.12
Requires-Python: >=3.11
License-File: LICENSE
Requires-Dist: numpy
Requires-Dist: setuptools
Requires-Dist: faker
Requires-Dist: requests
Requires-Dist: pandas
Requires-Dist: rich
Requires-Dist: pytz
Provides-Extra: dev
Requires-Dist: pre-commit; extra == "dev"
Requires-Dist: pytest; extra == "dev"
Requires-Dist: pytest-cov; extra == "dev"
Requires-Dist: versioneer; extra == "dev"
Provides-Extra: docs
Requires-Dist: ipython; extra == "docs"
Requires-Dist: jupyter-sphinx; extra == "docs"
Requires-Dist: myst-nb; extra == "docs"
Requires-Dist: numpydoc; extra == "docs"
Requires-Dist: pre-commit; extra == "docs"
Requires-Dist: sphinx>=5; extra == "docs"
Requires-Dist: sphinx-copybutton; extra == "docs"
Requires-Dist: sphinx-design; extra == "docs"
Requires-Dist: sphinx-notfound-page; extra == "docs"
Requires-Dist: sphinx-sitemap; extra == "docs"
Requires-Dist: sphinx-codeautolink; extra == "docs"
Requires-Dist: sphinxcontrib-bibtex; extra == "docs"
Requires-Dist: pydata-sphinx-theme; extra == "docs"
Requires-Dist: watermark; extra == "docs"
